gruetils/__init__.py
gruetils/collections/__init__.py
gruetils-0.0.2.dist-info/LICENSE
gruetils-0.0.2.dist-info/METADATA
gruetils-0.0.2.dist-info/WHEEL
gruetils-0.0.2.dist-info/top_level.txt
gruetils-0.0.2.dist-info/RECORD
