Metadata-Version: 2.1
Name: gruetils
Version: 0.0.2
Summary: Small utilities used in many of my projects
Home-page: UNKNOWN
Author: Daniel S
License: DBADPL
Platform: UNKNOWN
Classifier: Programming Language :: Python :: 3
Classifier: Development Status :: 2 - Pre-Alpha
Classifier: Operating System :: OS Independent
Classifier: License :: Other/Proprietary License
Classifier: Topic :: Utilities
